Metadata-Version: 2.4
Name: cli-mcp-server
Version: 0.2.5
Summary: Command line interface for MCP clients with secure execution and customizable security policies
Project-URL: Homepage, https://github.com/MladenSU/cli-mcp-server
Project-URL: Documentation, https://github.com/MladenSU/cli-mcp-server#readme
Project-URL: Repository, https://github.com/MladenSU/cli-mcp-server.git
Project-URL: Bug Tracker, https://github.com/MladenSU/cli-mcp-server/issues
Author-email: Mladen <fangs-lever6n@icloud.com>
License-File: LICENSE
Requires-Python: >=3.10
Requires-Dist: mcp>=1.10.1
